seedream5_ai/__init__.py
seedream5_ai-0.1.0.dist-info/licenses/LICENSE
seedream5_ai-0.1.0.dist-info/METADATA
seedream5_ai-0.1.0.dist-info/WHEEL
seedream5_ai-0.1.0.dist-info/top_level.txt
seedream5_ai-0.1.0.dist-info/RECORD
