Metadata-Version: 2.4
Name: seedream5-ai
Version: 0.1.0
Summary: AI-powered video generation platform - High-quality integration with seedream5ai.org
Home-page: https://seedream5ai.org
Author-email: Seedream5 Team <contact@seedream5ai.org>
License: MIT
Project-URL: Homepage, https://seedream5ai.org
Project-URL: Documentation, https://seedream5ai.org
Project-URL: Repository, https://github.com/seedream5/seedream5
Project-URL: Website, https://seedream5ai.org
Keywords: ai,video,generation,seedream5,artificial-intelligence
Classifier: Development Status :: 4 - Beta
Classifier: Intended Audience :: Developers
Classifier: License :: OSI Approved :: MIT License
Classifier: Programming Language :: Python :: 3
Classifier: Programming Language :: Python :: 3.9
Classifier: Programming Language :: Python :: 3.10
Classifier: Programming Language :: Python :: 3.11
Classifier: Programming Language :: Python :: 3.12
Classifier: Topic :: Multimedia :: Video
Classifier: Topic :: Scientific/Engineering :: Artificial Intelligence
Requires-Python: >=3.9
License-File: LICENSE
Dynamic: home-page
Dynamic: license-file
Dynamic: requires-python
